setup.py
django_uwsgi_mail.egg-info/PKG-INFO
django_uwsgi_mail.egg-info/SOURCES.txt
django_uwsgi_mail.egg-info/dependency_links.txt
django_uwsgi_mail.egg-info/top_level.txt
uwsgi_mail/__init__.py
uwsgi_mail/task.py
uwsgi_mail/uwsgi.py