Metadata-Version: 1.0
Name: django-uwsgi-mail
Version: 1.0
Summary: A Django backend for e-mail delivery using uWSGI Spool to queue deliveries.
Home-page: https://github.com/jaysonsantos/django-uwsgi-mail
Author: Jayson Reis
Author-email: santosdosreis@gmail.com
License: UNKNOWN
Platform: UNKNOWN
Classifier: Development Status :: 4 - Beta
Classifier: License :: OSI Approved :: MIT License
Classifier: Operating System :: OS Independent
